jupyter_o2/__init__.py
jupyter_o2/__main__.py
jupyter_o2/_version.py
jupyter_o2/config_manager.py
jupyter_o2/jupyter-o2.cfg
jupyter_o2/jupyter_o2.py
jupyter_o2/pysectools.py
jupyter_o2/utils.py
jupyter_o2-1.1.4.dist-info/LICENSE
jupyter_o2-1.1.4.dist-info/METADATA
jupyter_o2-1.1.4.dist-info/WHEEL
jupyter_o2-1.1.4.dist-info/entry_points.txt
jupyter_o2-1.1.4.dist-info/top_level.txt
jupyter_o2-1.1.4.dist-info/RECORD
