Metadata-Version: 2.1
Name: jupyter-o2
Version: 1.1.4
Summary: Run Jupyter on Orchestra 2
Home-page: https://github.com/aaronkollasch/jupyter-o2
Author: Aaron Kollasch
Author-email: aaron@kollasch.dev
License: MIT
Keywords: jupyter,remote,ssh,slurm,pexpect,orchestra,o2
Platform: any
Classifier: Development Status :: 5 - Production/Stable
Classifier: Intended Audience :: Developers
Classifier: Intended Audience :: System Administrators
Classifier: Intended Audience :: Science/Research
Classifier: Environment :: Console
Classifier: Operating System :: MacOS :: MacOS X
Classifier: Operating System :: POSIX
Classifier: Topic :: Utilities
Classifier: License :: OSI Approved :: MIT License
Classifier: Programming Language :: Python :: 3
Classifier: Programming Language :: Python :: 3.6
Classifier: Programming Language :: Python :: 3.7
Classifier: Programming Language :: Python :: 3.8
Classifier: Programming Language :: Python :: 3.9
Requires-Python: >=3.6
License-File: LICENSE
Requires-Dist: pexpect (>=4.5)
Requires-Dist: dnspython (>=2.0)
Requires-Dist: pyobjc-framework-Quartz (>=4) ; platform_system == "Darwin"
Provides-Extra: test
Requires-Dist: tox ; extra == 'test'
Requires-Dist: pytest ; extra == 'test'
Requires-Dist: coverage ; extra == 'test'
